url_matcher/__init__.py
url_matcher/__version__.py
url_matcher/example.py
url_matcher/matcher.py
url_matcher/patterns.py
url_matcher/util.py
url_matcher-0.5.0.dist-info/LICENSE
url_matcher-0.5.0.dist-info/METADATA
url_matcher-0.5.0.dist-info/WHEEL
url_matcher-0.5.0.dist-info/top_level.txt
url_matcher-0.5.0.dist-info/RECORD
