Metadata-Version: 2.1
Name: url-matcher
Version: 0.5.0
Summary: URL matching rules library to connect URLs with resources
Home-page: https://github.com/zytedata/url-matcher
Author: Zyte Group Ltd
Author-email: info@zyte.com
Classifier: Development Status :: 3 - Alpha
Classifier: Intended Audience :: Developers
Classifier: License :: OSI Approved :: BSD License
Classifier: Natural Language :: English
Classifier: Operating System :: OS Independent
Classifier: Programming Language :: Python :: 3
Classifier: Programming Language :: Python :: 3.8
Classifier: Programming Language :: Python :: 3.9
Classifier: Programming Language :: Python :: 3.10
Classifier: Programming Language :: Python :: 3.11
Classifier: Programming Language :: Python :: 3.12
Requires-Python: >=3.8
License-File: LICENSE
Requires-Dist: tldextract>=1.2
